pmf_music_player/__init__.py
pmf_music_player/music_player.py
pmf_music_player-0.0.1.dist-info/LICENSE
pmf_music_player-0.0.1.dist-info/METADATA
pmf_music_player-0.0.1.dist-info/WHEEL
pmf_music_player-0.0.1.dist-info/top_level.txt
pmf_music_player-0.0.1.dist-info/RECORD
